LICENSE.txt
MANIFEST.in
README.rst
setup.cfg
setup.py
acquiring_sdk_python.egg-info/PKG-INFO
acquiring_sdk_python.egg-info/SOURCES.txt
acquiring_sdk_python.egg-info/dependency_links.txt
acquiring_sdk_python.egg-info/requires.txt
acquiring_sdk_python.egg-info/top_level.txt
worldline/__init__.py
worldline/acquiring/__init__.py
worldline/acquiring/sdk/__init__.py
worldline/acquiring/sdk/api_resource.py
worldline/acquiring/sdk/call_context.py
worldline/acquiring/sdk/client.py
worldline/acquiring/sdk/communicator.py
worldline/acquiring/sdk/communicator_configuration.py
worldline/acquiring/sdk/factory.py
worldline/acquiring/sdk/proxy_configuration.py
worldline/acquiring/sdk/authentication/__init__.py
worldline/acquiring/sdk/authentication/authenticator.py
worldline/acquiring/sdk/authentication/authorization_type.py
worldline/acquiring/sdk/authentication/oauth2_authenticator.py
worldline/acquiring/sdk/authentication/oauth2_exception.py
worldline/acquiring/sdk/authentication/oauth2_scopes.py
worldline/acquiring/sdk/communication/__init__.py
worldline/acquiring/sdk/communication/communication_exception.py
worldline/acquiring/sdk/communication/connection.py
worldline/acquiring/sdk/communication/default_connection.py
worldline/acquiring/sdk/communication/metadata_provider.py
worldline/acquiring/sdk/communication/multipart_form_data_object.py
worldline/acquiring/sdk/communication/multipart_form_data_request.py
worldline/acquiring/sdk/communication/not_found_exception.py
worldline/acquiring/sdk/communication/param_request.py
worldline/acquiring/sdk/communication/pooled_connection.py
worldline/acquiring/sdk/communication/request_header.py
worldline/acquiring/sdk/communication/request_param.py
worldline/acquiring/sdk/communication/response_exception.py
worldline/acquiring/sdk/communication/response_header.py
worldline/acquiring/sdk/domain/__init__.py
worldline/acquiring/sdk/domain/data_object.py
worldline/acquiring/sdk/domain/shopping_cart_extension.py
worldline/acquiring/sdk/domain/uploadable_file.py
worldline/acquiring/sdk/json/__init__.py
worldline/acquiring/sdk/json/default_marshaller.py
worldline/acquiring/sdk/json/marshaller.py
worldline/acquiring/sdk/json/marshaller_syntax_exception.py
