Metadata-Version: 2.1
Name: acquiring-sdk-python
Version: 1.3.0
Summary: SDK to communicate with the Worldline Acquiring platform using the Worldline Acquiring API
Home-page: https://github.com/Worldline-Acquiring/acquiring-sdk-python
Author: Worldline Acquiring
Author-email: github.acquiring@worldline.com
License: MIT
Keywords: Worldline Acquiring SDK
Platform: python 3.7
Classifier: Development Status :: 5 - Production/Stable
Classifier: Operating System :: POSIX :: Linux
Classifier: Operating System :: Microsoft :: Windows
Classifier: Intended Audience :: Developers
Classifier: Programming Language :: Python :: 3 :: Only
Classifier: Programming Language :: Python :: 3.7
Classifier: Programming Language :: Python :: 3.8
Classifier: Programming Language :: Python :: 3.9
Classifier: Programming Language :: Python :: 3.10
Classifier: Programming Language :: Python :: 3.11
Classifier: Programming Language :: Python :: 3.12
Classifier: Programming Language :: Python :: 3.13
Classifier: Topic :: Office/Business :: Financial
Classifier: License :: OSI Approved :: MIT License
Requires-Python: >= 3.7
License-File: LICENSE.txt
